getpass4/__getpass4__.py
getpass4/__init__.py
getpass4/__output__.py
getpass4/__pass__.py
getpass4/gp4_help.py
getpass4/kaka.py
getpass4-0.0.14.1.dist-info/LICENSE
getpass4-0.0.14.1.dist-info/METADATA
getpass4-0.0.14.1.dist-info/WHEEL
getpass4-0.0.14.1.dist-info/licence.txt
getpass4-0.0.14.1.dist-info/top_level.txt
getpass4-0.0.14.1.dist-info/RECORD
